behave_http/__init__.py
behave_http/environment.py
behave_http/utils.py
behave_http/steps/__init__.py
behave_http-0.1.1.dist-info/DESCRIPTION.rst
behave_http-0.1.1.dist-info/METADATA
behave_http-0.1.1.dist-info/RECORD
behave_http-0.1.1.dist-info/WHEEL
behave_http-0.1.1.dist-info/metadata.json
behave_http-0.1.1.dist-info/top_level.txt
