Metadata-Version: 2.0
Name: behave-http
Version: 0.1.1
Summary: Behave HTTP steps
Home-page: https://github.com/mikek/behave-http
Author: Mykhailo Kolesnyk
Author-email: mike@openbunker.org
License: BSD 2-Clause
Platform: UNKNOWN
Classifier: Programming Language :: Python
Classifier: Programming Language :: Python :: 2
Classifier: Programming Language :: Python :: 2.7
Classifier: Programming Language :: Python :: 3
Classifier: Programming Language :: Python :: 3.3
Classifier: Programming Language :: Python :: 3.4
Classifier: Programming Language :: Python :: 3.5
Classifier: Development Status :: 4 - Beta
Classifier: Natural Language :: English
Classifier: Environment :: Web Environment
Classifier: Intended Audience :: Developers
Classifier: Operating System :: OS Independent
Classifier: Topic :: Software Development :: Libraries :: Python Modules
Classifier: Topic :: Internet :: WWW/HTTP :: Dynamic Content
Classifier: Topic :: Software Development :: Testing
Requires-Dist: behave (>=1.2.4)
Requires-Dist: Jinja2 (>=2.5)
Requires-Dist: jpath (>=1.1)
Requires-Dist: ensure (>=0.1.6)
Requires-Dist: purl (>=0.6)
Requires-Dist: requests (>=2.0.0)
